lilliepy_socket/__init__.py
lilliepy_socket/main.py
lilliepy_socket-1.0.dist-info/METADATA
lilliepy_socket-1.0.dist-info/WHEEL
lilliepy_socket-1.0.dist-info/top_level.txt
lilliepy_socket-1.0.dist-info/RECORD
